{
  "items": [
    {
      "id": "Paasparty",
      "titel": "Paasparty Bentelo",
      "datum": "2026-04-05",
      "tijdstip": "19:00 – 20:00 uur",
      "locatie": "Feestterrein Paasparty, Bentelo",
      "beschrijving": "",
      "label": "",
      "hoofd": false
    },
    {
      "id": "Tuigpaarden show De Hoffmeier",
      "titel": "Manege De Hoffmeier",
      "datum": "2026-04-11",
      "tijdstip": "Vanaf 19.00 uur",
      "locatie": "Manege De Hoffmeier",
      "beschrijving": "Tuigpaarden show",
      "label": "",
      "hoofd": false
    },
    {
      "id": "Hollandmarkt (DE)",
      "titel": "Hollandmarkt (DE) (gecanceld)",
      "datum": "2026-05-10",
      "tijdstip": "Hele dag. ",
      "locatie": "Holland markt Bergkamen (DE)",
      "beschrijving": "",
      "label": "",
      "hoofd": false
    },
    {
      "id": "Wandelvierdaagse",
      "titel": "Wandelvierdaagse Delden",
      "datum": "2026-06-12",
      "tijdstip": "19:00 – 21:00 uur",
      "locatie": "Centrum van Delden",
      "beschrijving": "Intocht wandelvierdaagse Delden",
      "label": "",
      "hoofd": false
    },
    {
      "id": "Dweildag",
      "titel": "De Bos Dweildag (optie)",
      "datum": "2026-09-12",
      "tijdstip": "Vanaf 10:00 uur",
      "locatie": "Centrum van Zutphen",
      "beschrijving": "",
      "label": "",
      "hoofd": false
    },
    {
      "hoofd": false,
      "id": "Opendag  Zorgboederij ",
      "titel": "Opendag  Erve Knippert (In Aanvraag)",
      "datum": "2026-06-06",
      "tijdstip": "10.30 tot 15.30 uur",
      "locatie": "Haaksbergen",
      "beschrijving": "Opendag zorgboerderij Knippert"
    },
    {
      "hoofd": false,
      "id": "Verrassings optreden",
      "titel": "Verrassingsoptreden Lintje AN",
      "datum": "2026-04-24",
      "tijdstip": "21.00 tot 22.00 uur",
      "locatie": "Bentelo"
    }
  ]
}
